dnjs/__init__.py
dnjs/builtins.py
dnjs/cli.py
dnjs/css.py
dnjs/grammar.lark
dnjs/html.py
dnjs/interpreter.py
dnjs/parser.py
dnjs/tokeniser.py
test/__init__.py
test/conftest.py
test/test_html.py
test/test_interpereter.py
test/test_parser.py
test/test_tokeniser.py
dnjs-0.0.12.dist-info/LICENSE
dnjs-0.0.12.dist-info/METADATA
dnjs-0.0.12.dist-info/WHEEL
dnjs-0.0.12.dist-info/entry_points.txt
dnjs-0.0.12.dist-info/top_level.txt
dnjs-0.0.12.dist-info/RECORD
