Metadata-Version: 2.1
Name: dnjs
Version: 0.0.12
Summary: DOM Notation JS
Home-page: https://github.com/leontrolski/dnjs
Author: Leon Trolski
Author-email: ojhrussell@gmail.com
License: UNKNOWN
Platform: UNKNOWN
Classifier: Programming Language :: Python :: 3
Classifier: Operating System :: OS Independent
Requires-Dist: beautifulsoup4
Requires-Dist: click
Provides-Extra: dev
Requires-Dist: black ; extra == 'dev'
Requires-Dist: icdiff ; extra == 'dev'
Requires-Dist: pip-tools ; extra == 'dev'
Requires-Dist: prettyprinter ; extra == 'dev'
Requires-Dist: pytest ; extra == 'dev'
